Workbook
Name Aporte: 'Simulador APP Perfil Investidor'!$D$16
Name Aporte: 'Simulador - Nomeando intervalos'!$D$15
Name Dividendos_Mensais: 'Simulador APP Perfil Investidor'!$D$20
Name Dividendos_Mensais: 'Simulador - Nomeando intervalos'!$D$19
Name Patrimonio: 'Simulador APP Perfil Investidor'!$D$19
Name Patrimonio: 'Simulador - Nomeando intervalos'!$D$18
Name Qtd_Anos: 'Simulador APP Perfil Investidor'!$D$17
Name Qtd_Anos: 'Simulador - Nomeando intervalos'!$D$16
Name Rendimento_Carteira: 'Simulador APP Perfil Investidor'!$D$12
Name Rendimento_Carteira: 'Simulador - Nomeando intervalos'!$D$11
Name Salario: 'Simulador APP Perfil Investidor'!$D$11
Name Salario: 'Simulador - Nomeando intervalos'!$D$10
Name Sugestao_Investimento: 'Simulador APP Perfil Investidor'!$D$13
Name Sugestao_Investimento: 'Simulador - Nomeando intervalos'!$D$12
Name Taxa_Mensal: 'Simulador APP Perfil Investidor'!$D$18
Name Taxa_Mensal: 'Simulador - Nomeando intervalos'!$D$17

Sheet Simulador - Patrimonio, Cenário
B12: INVESTIMENTO MENSAL
B13: Quanto investir por mês? | C13: 500
B14: Por quantos anos? | C14: 5
B15: Taxa de Rendimento Mensal? | C15: 0.01079
B16: Patrimonio acumulado? | C16: =FV(C15,C14*12,C13*-1) -> 41888.457
B17: Dividendos mensais? | C17: =C16*1% -> 418.88457
B19: CENÁRIOS | D19: Dividendo
A20: 2 | B20: Quanto em 2 anos? | C20: =FV($C$15,A20*12,$C$13*-1) -> 13613.814 | D20: =C20*1% -> 136.13814
A21: 5 | B21: Quanto em 5 anos? | C21: =FV($C$15,A21*12,$C$13*-1) -> 41888.457 | D21: =C21*1% -> 418.88457
A22: 10 | B22: Quanto em 10 anos? | C22: =FV($C$15,A22*12,$C$13*-1) -> 121642.11 | D22: =C22*1% -> 1216.4211
A23: 20 | B23: Quanto em 20 anos? | C23: =FV($C$15,A23*12,$C$13*-1) -> 562599.2 | D23: =C23*1% -> 5625.992
A24: 30 | B24: Quanto em 30 anos? | C24: =FV($C$15,A24*12,$C$13*-1) -> 2161084.8 | D24: =C24*1% -> 21610.848

Sheet Simulador - Variaveis Globais
B12: INVESTIMENTO MENSAL | E12: Configurações
B13: Quanto investir por mês? | C13: 500 | E13: Salário | F13: 5000
B14: Por quantos anos? | C14: 5 | E14: Rendimento Carteira | F14: 0.01
B15: Taxa de Rendimento Mensal? | C15: 0.01079 | E15: Sugestão de Investimento | F15: =F13*30% -> 1500
B16: Patrimonio acumulado? | C16: =FV(C15,C14*12,C13*-1) -> 41888.457
B17: Dividendos mensais? | C17: =C16*$F$14 -> 418.88457
B19: CENÁRIOS | D19: Dividendo
A20: 2 | B20: Quanto em 2 anos? | C20: =FV($C$15,A20*12,$C$13*-1) -> 13613.814 | D20: =C20*$F$14 -> 136.13814
A21: 5 | B21: Quanto em 5 anos? | C21: =FV($C$15,A21*12,$C$13*-1) -> 41888.457 | D21: =C21*$F$14 -> 418.88457
A22: 10 | B22: Quanto em 10 anos? | C22: =FV($C$15,A22*12,$C$13*-1) -> 121642.11 | D22: =C22*$F$14 -> 1216.4211
A23: 20 | B23: Quanto em 20 anos? | C23: =FV($C$15,A23*12,$C$13*-1) -> 562599.2 | D23: =C23*$F$14 -> 5625.992
A24: 30 | B24: Quanto em 30 anos? | C24: =FV($C$15,A24*12,$C$13*-1) -> 2161084.8 | D24: =C24*$F$14 -> 21610.848

Sheet Simulador - Nomeando intervalos
B9: CONFIGURAÇÕES
B10: Salário | D10: 5000
B11: Rendimento Carteira | D11: 0.006
B12: Sugestão de Investimento | D12: =D10*30% -> 1500
B14: INVESTIMENTO MENSAL
B15: Quanto investir por mês? | D15: 500
B16: Por quantos anos? | D16: 5
B17: Taxa de Rendimento Mensal? | D17: 0.01079
B18: Patrimonio acumulado? | D18: =FV(Taxa_Mensal,Qtd_Anos*12,Aporte*-1) -> 41888.457
B19: Dividendos mensais? | D19: =Patrimonio*Rendimento_Carteira -> 251.33074
B21: CENÁRIOS | D21: Dividendo
A22: 2 | B22: Quanto em 2 anos? | C22: =FV($D$17,A22*12,$D$15*-1) -> 13613.814 | D22: =C22*Rendimento_Carteira -> 81.682882
A23: 5 | B23: Quanto em 5 anos? | C23: =FV($D$17,A23*12,$D$15*-1) -> 41888.457 | D23: =C23*Rendimento_Carteira -> 251.33074
A24: 10 | B24: Quanto em 10 anos? | C24: =FV($D$17,A24*12,$D$15*-1) -> 121642.11 | D24: =C24*Rendimento_Carteira -> 729.85264
A25: 20 | B25: Quanto em 20 anos? | C25: =FV($D$17,A25*12,$D$15*-1) -> 562599.2 | D25: =C25*Rendimento_Carteira -> 3375.5952
A26: 30 | B26: Quanto em 30 anos? | C26: =FV($D$17,A26*12,$D$15*-1) -> 2161084.8 | D26: =C26*Rendimento_Carteira -> 12966.509

Sheet Tabela Apoio - Perfil
A2: CHAVE | B2: PERFIL | C2: TIPO DE FII | D2: %
A3: =$B$3&"-"&C3 -> Conservador-PAPEL | B3: Conservador | C3: PAPEL | D3: 0.3 | H3: %
A4: =$B$3&"-"&C4 -> Conservador-TIJOLO | B4: Conservador | C4: TIJOLO | D4: 0.5
A5: =$B$3&"-"&C5 -> Conservador-HÍBRIDOS | B5: Conservador | C5: HÍBRIDOS | D5: 0.1
A6: =$B$3&"-"&C6 -> Conservador-FOFs | B6: Conservador | C6: FOFs | D6: 0.1
A7: =$B$3&"-"&C7 -> Conservador-DESENVOLVIMENTO | B7: Conservador | C7: DESENVOLVIMENTO | D7: 0
A8: =$B$3&"-"&C8 -> Conservador-HOTELARIAS | B8: Conservador | C8: HOTELARIAS | D8: 0
A9: =$B$9&"-"&C9 -> Moderado-PAPEL | B9: Moderado | C9: PAPEL | D9: 0.32
A10: =$B$9&"-"&C10 -> Moderado-TIJOLO | B10: Moderado | C10: TIJOLO | D10: 0.35
A11: =$B$9&"-"&C11 -> Moderado-HÍBRIDOS | B11: Moderado | C11: HÍBRIDOS | D11: 0.08
A12: =$B$9&"-"&C12 -> Moderado-FOFs | B12: Moderado | C12: FOFs | D12: 0.05
A13: =$B$9&"-"&C13 -> Moderado-DESENVOLVIMENTO | B13: Moderado | C13: DESENVOLVIMENTO | D13: 0.1
A14: =$B$9&"-"&C14 -> Moderado-HOTELARIAS | B14: Moderado | C14: HOTELARIAS | D14: 0.1
A15: =$B$15&"-"&C15 -> Agressivo-PAPEL | B15: Agressivo | C15: PAPEL | D15: 0.5
A16: =$B$15&"-"&C16 -> Agressivo-TIJOLO | B16: Agressivo | C16: TIJOLO | D16: 0.1
A17: =$B$15&"-"&C17 -> Agressivo-HÍBRIDOS | B17: Agressivo | C17: HÍBRIDOS | D17: 0.05
A18: =$B$15&"-"&C18 -> Agressivo-FOFs | B18: Agressivo | C18: FOFs | D18: 0.05
A19: =$B$15&"-"&C19 -> Agressivo-DESENVOLVIMENTO | B19: Agressivo | C19: DESENVOLVIMENTO | D19: 0.2
A20: =$B$15&"-"&C20 -> Agressivo-HOTELARIAS | B20: Agressivo | C20: HOTELARIAS | D20: 0.1

Sheet Simulador APP Perfil Investidor
B10: CONFIGURAÇÕES
B11: Salário | D11: 5000
B12: Rendimento Carteira | D12: 0.0085
B13: Sugestão de Investimento | D13: =D11*30% -> 1500
B15: INVESTIMENTO MENSAL
B16: Quanto investir por mês? | D16: 800
B17: Por quantos anos? | D17: 5
B18: Taxa de Rendimento Mensal? | D18: 0.01079
B19: Patrimonio acumulado? | D19: =FV(Taxa_Mensal,Qtd_Anos*12,Aporte*-1) -> 67021.531
B20: Dividendos mensais? | D20: =Patrimonio*Rendimento_Carteira -> 569.68302
B22: CENÁRIOS | D22: Dividendo
A23: 2 | B23: Quanto em 2 anos? | C23: =FV($D$18,A23*12,$D$16*-1) -> 21782.102 | D23: =C23*Rendimento_Carteira -> 185.14787
A24: 5 | B24: Quanto em 5 anos? | C24: =FV($D$18,A24*12,$D$16*-1) -> 67021.531 | D24: =C24*Rendimento_Carteira -> 569.68302
A25: 10 | B25: Quanto em 10 anos? | C25: =FV($D$18,A25*12,$D$16*-1) -> 194627.37 | D25: =C25*Rendimento_Carteira -> 1654.3326
A26: 20 | B26: Quanto em 20 anos? | C26: =FV($D$18,A26*12,$D$16*-1) -> 900158.72 | D26: =C26*Rendimento_Carteira -> 7651.3491
A27: 30 | B27: Quanto em 30 anos? | C27: =FV($D$18,A27*12,$D$16*-1) -> 3457735.7 | D27: =C27*Rendimento_Carteira -> 29390.754
B29: PERFIL | C29: Conservador
B30: VALOR A SER INVESTIDO POR MÊS | C30: =Aporte -> 800
B31: TIPO DE FII | C31: Percentual Sugerido | D31: Valores
B32: PAPEL | C32: =VLOOKUP($C$29&"-"&B32,'Tabela Apoio - Perfil'!A:D,4,FALSE) -> 0.3 | D32: =C32*$C$30 -> 240
B33: TIJOLO | C33: =VLOOKUP($C$29&"-"&B33,'Tabela Apoio - Perfil'!A:D,4,FALSE) -> 0.5 | D33: =C33*$C$30 -> 400
B34: HÍBRIDOS | C34: =VLOOKUP($C$29&"-"&B34,'Tabela Apoio - Perfil'!A:D,4,FALSE) -> 0.1 | D34: =C34*$C$30 -> 80
B35: FOFs | C35: =VLOOKUP($C$29&"-"&B35,'Tabela Apoio - Perfil'!A:D,4,FALSE) -> 0.1 | D35: =C35*$C$30 -> 80
B36: DESENVOLVIMENTO | C36: =VLOOKUP($C$29&"-"&B36,'Tabela Apoio - Perfil'!A:D,4,FALSE) -> 0 | D36: =C36*$C$30 -> 0
B37: HOTELARIAS | C37: =VLOOKUP($C$29&"-"&B37,'Tabela Apoio - Perfil'!A:D,4,FALSE) -> 0 | D37: =C37*$C$30 -> 0
B38: TOTAL | D38: =SUM(D32:D37) -> 800
